LICENSE.txt
MANIFEST.in
README.md
setup.py
htam/__init__.py
htam.egg-info/PKG-INFO
htam.egg-info/SOURCES.txt
htam.egg-info/dependency_links.txt
htam.egg-info/top_level.txt
tests/test.py