Metadata-Version: 2.1
Name: htam
Version: 2.0.9
Summary: Math package with 15 useful math functions like prime-counting function or modular congruences solver. Now it also includes 1 class that performs a very useful search. This package is in constant improvement and you can email me to give me any idea.
Home-page: https://github.com/Zslez/htam
Author: Cristiano Sansò
Author-email: cristiano.sanso.04@gmail.com
License: UNKNOWN
Platform: UNKNOWN
Classifier: Programming Language :: Python :: 3
Classifier: License :: OSI Approved :: MIT License
Requires-Python: >=3
